{
  "generated_at": "2026-07-11T13:38:18Z",
  "git_head": "df4763374d4253a118669affd40b5b4835e61950",
  "days": [
    {
      "date": "2026-07-09",
      "prs_merged": 45,
      "commits": 46,
      "session_cards": 29,
      "test_functions_eod": 106
    },
    {
      "date": "2026-07-10",
      "prs_merged": 36,
      "commits": 39,
      "session_cards": 21,
      "test_functions_eod": 178
    },
    {
      "date": "2026-07-11",
      "prs_merged": 45,
      "commits": 64,
      "session_cards": 22,
      "test_functions_eod": 250,
      "partial": true
    }
  ],
  "totals": {
    "prs_merged": 126,
    "commits": 149,
    "session_cards": 72,
    "test_functions": 250,
    "services": 4
  }
}
